[
  {
    "LocationId": 1,
    "Latitude": 29.71376729,
    "Longitude": -91.1972466
  },
  {
    "LocationId": 2,
    "Latitude": 30.26616881,
    "Longitude": -89.77434616
  },
  {
    "LocationId": 3,
    "Latitude": 29.97877,
    "Longitude": -92.12464
  },
  {
    "LocationId": 4,
    "Latitude": 29.97900457,
    "Longitude": -92.12437146
  },
  {
    "LocationId": 5,
    "Latitude": 30.75227525,
    "Longitude": -89.84950307
  },
  {
    "LocationId": 6,
    "Latitude": 31.92619386,
    "Longitude": -92.63911313
  },
  {
    "LocationId": 7,
    "Latitude": 31.90884237,
    "Longitude": -92.62959313
  },
  {
    "LocationId": 8,
    "Latitude": 31.12361261,
    "Longitude": -92.05746465
  },
  {
    "LocationId": 9,
    "Latitude": 30.44751977,
    "Longitude": -93.42683736
  },
  {
    "LocationId": 10,
    "Latitude": 30.20770289,
    "Longitude": -92.66096605
  },
  {
    "LocationId": 11,
    "Latitude": 30.22354307,
    "Longitude": -92.65773502
  },
  {
    "LocationId": 12,
    "Latitude": 30.01027304,
    "Longitude": -90.25482519
  },
  {
    "LocationId": 13,
    "Latitude": 29.93475773,
    "Longitude": -90.08425384
  },
  {
    "LocationId": 14,
    "Latitude": 29.92653514,
    "Longitude": -90.09578133
  },
  {
    "LocationId": 15,
    "Latitude": 29.95124349,
    "Longitude": -90.07729829
  },
  {
    "LocationId": 16,
    "Latitude": 30.5168133,
    "Longitude": -90.45007396
  },
  {
    "LocationId": 17,
    "Latitude": 30.17802297,
    "Longitude": -93.20946513
  },
  {
    "LocationId": 18,
    "Latitude": 30.23883367,
    "Longitude": -93.37716845
  },
  {
    "LocationId": 19,
    "Latitude": 30.49542401,
    "Longitude": -92.40651872
  },
  {
    "LocationId": 20,
    "Latitude": 30.2705881,
    "Longitude": -89.78401836
  },
  {
    "LocationId": 21,
    "Latitude": 30.50895357,
    "Longitude": -90.48206949
  },
  {
    "LocationId": 22,
    "Latitude": 31.13949984,
    "Longitude": -93.26081635
  },
  {
    "LocationId": 23,
    "Latitude": 30.22837977,
    "Longitude": -92.6560989
  },
  {
    "LocationId": 24,
    "Latitude": 30.2265354,
    "Longitude": -92.01218535
  },
  {
    "LocationId": 25,
    "Latitude": 32.7709118,
    "Longitude": -91.89597831
  },
  {
    "LocationId": 26,
    "Latitude": 29.94350932,
    "Longitude": -90.07682982
  },
  {
    "LocationId": 27,
    "Latitude": 29.9578748,
    "Longitude": -90.09004783
  },
  {
    "LocationId": 28,
    "Latitude": 32.50322374,
    "Longitude": -92.11297356
  },
  {
    "LocationId": 29,
    "Latitude": 30.50010845,
    "Longitude": -92.43417662
  },
  {
    "LocationId": 30,
    "Latitude": 30.54743523,
    "Longitude": -92.0818735
  },
  {
    "LocationId": 31,
    "Latitude": 30.26841583,
    "Longitude": -91.90471716
  },
  {
    "LocationId": 32,
    "Latitude": 29.68662878,
    "Longitude": -91.1542151
  },
  {
    "LocationId": 33,
    "Latitude": 30.4842264,
    "Longitude": -90.09479922
  },
  {
    "LocationId": 34,
    "Latitude": 30.35723857,
    "Longitude": -90.06606197
  },
  {
    "LocationId": 35,
    "Latitude": 30.4284703,
    "Longitude": -90.03954872
  },
  {
    "LocationId": 36,
    "Latitude": 30.45149806,
    "Longitude": -93.42433125
  },
  {
    "LocationId": 37,
    "Latitude": 30.77759807,
    "Longitude": -89.85393103
  },
  {
    "LocationId": 38,
    "Latitude": 30.85135915,
    "Longitude": -93.28951408
  },
  {
    "LocationId": 39,
    "Latitude": 32.03747785,
    "Longitude": -93.70833302
  },
  {
    "LocationId": 40,
    "Latitude": 32.5315709,
    "Longitude": -92.64415316
  },
  {
    "LocationId": 41,
    "Latitude": 32.78163336,
    "Longitude": -91.90124782
  },
  {
    "LocationId": 42,
    "Latitude": 30.08703539,
    "Longitude": -90.50265109
  },
  {
    "LocationId": 43,
    "Latitude": 30.50333727,
    "Longitude": -90.4472413
  },
  {
    "LocationId": 44,
    "Latitude": 29.96626105,
    "Longitude": -92.12020475
  },
  {
    "LocationId": 45,
    "Latitude": 32.63214849,
    "Longitude": -93.2846288
  },
  {
    "LocationId": 46,
    "Latitude": 32.61626093,
    "Longitude": -93.2869947
  },
  {
    "LocationId": 47,
    "Latitude": 32.52306311,
    "Longitude": -92.63994952
  },
  {
    "LocationId": 48,
    "Latitude": 30.22712005,
    "Longitude": -90.91047626
  },
  {
    "LocationId": 49,
    "Latitude": 30.23977222,
    "Longitude": -90.91378626
  },
  {
    "LocationId": 50,
    "Latitude": 30.23611611,
    "Longitude": -90.91391103
  },
  {
    "LocationId": 51,
    "Latitude": 30.22600239,
    "Longitude": -90.93201062
  },
  {
    "LocationId": 52,
    "Latitude": 32.50838598,
    "Longitude": -93.75074947
  },
  {
    "LocationId": 53,
    "Latitude": 32.49976161,
    "Longitude": -93.72944859
  },
  {
    "LocationId": 54,
    "Latitude": 32.51192212,
    "Longitude": -93.75375477
  },
  {
    "LocationId": 55,
    "Latitude": 32.46355403,
    "Longitude": -93.7650361
  },
  {
    "LocationId": 56,
    "Latitude": 32.49785772,
    "Longitude": -93.73926783
  },
  {
    "LocationId": 57,
    "Latitude": 32.44172188,
    "Longitude": -93.7510708
  },
  {
    "LocationId": 58,
    "Latitude": 32.50330977,
    "Longitude": -93.7388873
  },
  {
    "LocationId": 59,
    "Latitude": 32.50101197,
    "Longitude": -93.7382376
  },
  {
    "LocationId": 60,
    "Latitude": 32.49791277,
    "Longitude": -93.74556206
  },
  {
    "LocationId": 61,
    "Latitude": 32.49839657,
    "Longitude": -93.73723193
  },
  {
    "LocationId": 62,
    "Latitude": 32.48208077,
    "Longitude": -93.7064481
  },
  {
    "LocationId": 63,
    "Latitude": 30.21511337,
    "Longitude": -93.16409133
  },
  {
    "LocationId": 64,
    "Latitude": 30.22860617,
    "Longitude": -93.21693967
  },
  {
    "LocationId": 65,
    "Latitude": 30.1827191,
    "Longitude": -93.2137216
  },
  {
    "LocationId": 66,
    "Latitude": 30.44859717,
    "Longitude": -91.1719574
  },
  {
    "LocationId": 67,
    "Latitude": 30.45054457,
    "Longitude": -91.1761632
  },
  {
    "LocationId": 68,
    "Latitude": 30.48015112,
    "Longitude": -91.11462086
  },
  {
    "LocationId": 69,
    "Latitude": 30.38586332,
    "Longitude": -91.10813206
  },
  {
    "LocationId": 70,
    "Latitude": 30.44646723,
    "Longitude": -91.15528383
  },
  {
    "LocationId": 71,
    "Latitude": 30.44783627,
    "Longitude": -91.1535695
  },
  {
    "LocationId": 72,
    "Latitude": 30.48572946,
    "Longitude": -91.147471
  },
  {
    "LocationId": 73,
    "Latitude": 30.45380977,
    "Longitude": -91.1141218
  },
  {
    "LocationId": 74,
    "Latitude": 30.42746407,
    "Longitude": -91.08359456
  },
  {
    "LocationId": 75,
    "Latitude": 30.44875452,
    "Longitude": -91.16027406
  },
  {
    "LocationId": 76,
    "Latitude": 30.44311772,
    "Longitude": -91.1577681
  },
  {
    "LocationId": 77,
    "Latitude": 30.44916941,
    "Longitude": -91.17241214
  },
  {
    "LocationId": 78,
    "Latitude": "",
    "Longitude": ""
  },
  {
    "LocationId": 79,
    "Latitude": 32.15636987,
    "Longitude": -91.71610853
  },
  {
    "LocationId": 80,
    "Latitude": 32.16417057,
    "Longitude": -91.71468373
  },
  {
    "LocationId": 81,
    "Latitude": 30.22338547,
    "Longitude": -92.65777793
  },
  {
    "LocationId": 82,
    "Latitude": 29.90421477,
    "Longitude": -90.0532526
  },
  {
    "LocationId": 83,
    "Latitude": 29.96537849,
    "Longitude": -90.18948303
  },
  {
    "LocationId": 84,
    "Latitude": 30.23030207,
    "Longitude": -92.02265577
  },
  {
    "LocationId": 85,
    "Latitude": 30.21883427,
    "Longitude": -91.9923938
  },
  {
    "LocationId": 86,
    "Latitude": 30.23369004,
    "Longitude": -91.99812713
  },
  {
    "LocationId": 87,
    "Latitude": 30.20097597,
    "Longitude": -92.01324206
  },
  {
    "LocationId": 88,
    "Latitude": 30.21520995,
    "Longitude": -92.00696956
  },
  {
    "LocationId": 89,
    "Latitude": 30.23040217,
    "Longitude": -92.02278613
  },
  {
    "LocationId": 90,
    "Latitude": 30.25040504,
    "Longitude": -92.02266163
  },
  {
    "LocationId": 91,
    "Latitude": 30.21363922,
    "Longitude": -92.0098353
  },
  {
    "LocationId": 92,
    "Latitude": 29.78874269,
    "Longitude": -90.8147823
  },
  {
    "LocationId": 93,
    "Latitude": 29.79195217,
    "Longitude": -90.817181
  },
  {
    "LocationId": 94,
    "Latitude": 29.76993776,
    "Longitude": -90.8437556
  },
  {
    "LocationId": 95,
    "Latitude": 29.79595057,
    "Longitude": -90.8271918
  },
  {
    "LocationId": 96,
    "Latitude": 29.79478009,
    "Longitude": -90.83303046
  },
  {
    "LocationId": 97,
    "Latitude": 32.52951098,
    "Longitude": -92.6394249
  },
  {
    "LocationId": 98,
    "Latitude": 32.52749372,
    "Longitude": -92.63725833
  },
  {
    "LocationId": 99,
    "Latitude": 32.53063467,
    "Longitude": -92.6386825
  },
  {
    "LocationId": 100,
    "Latitude": 30.46653518,
    "Longitude": -90.9684025
  },
  {
    "LocationId": 101,
    "Latitude": 32.40787557,
    "Longitude": -91.1898592
  },
  {
    "LocationId": 102,
    "Latitude": 32.77613407,
    "Longitude": -91.91511686
  },
  {
    "LocationId": 103,
    "Latitude": 31.7525245,
    "Longitude": -93.05696553
  },
  {
    "LocationId": 104,
    "Latitude": 29.93958788,
    "Longitude": -90.10543943
  },
  {
    "LocationId": 105,
    "Latitude": 29.96258894,
    "Longitude": -90.08091956
  },
  {
    "LocationId": 106,
    "Latitude": 29.94047908,
    "Longitude": -90.0793636
  },
  {
    "LocationId": 107,
    "Latitude": 29.96399348,
    "Longitude": -90.08438787
  },
  {
    "LocationId": 108,
    "Latitude": 29.92982338,
    "Longitude": -90.0738536
  },
  {
    "LocationId": 109,
    "Latitude": 29.98200707,
    "Longitude": -90.10371493
  },
  {
    "LocationId": 110,
    "Latitude": 29.95445068,
    "Longitude": -90.07874503
  },
  {
    "LocationId": 111,
    "Latitude": 29.96006317,
    "Longitude": -90.07872513
  },
  {
    "LocationId": 112,
    "Latitude": 29.97355487,
    "Longitude": -90.08016579
  },
  {
    "LocationId": 113,
    "Latitude": 29.97506277,
    "Longitude": -90.10210029
  },
  {
    "LocationId": 114,
    "Latitude": 29.94854688,
    "Longitude": -90.06792193
  },
  {
    "LocationId": 115,
    "Latitude": 29.92192617,
    "Longitude": -90.10219369
  },
  {
    "LocationId": 116,
    "Latitude": 29.94096647,
    "Longitude": -90.05100326
  },
  {
    "LocationId": 117,
    "Latitude": 29.98811777,
    "Longitude": -90.0628776
  },
  {
    "LocationId": 118,
    "Latitude": 29.97436037,
    "Longitude": -90.0668123
  },
  {
    "LocationId": 119,
    "Latitude": 29.95641217,
    "Longitude": -90.0817582
  },
  {
    "LocationId": 120,
    "Latitude": 29.96643657,
    "Longitude": -90.09935103
  },
  {
    "LocationId": 121,
    "Latitude": 29.96412719,
    "Longitude": -90.06458936
  },
  {
    "LocationId": 122,
    "Latitude": 32.50888973,
    "Longitude": -92.10737093
  },
  {
    "LocationId": 123,
    "Latitude": 32.49131677,
    "Longitude": -92.09421776
  },
  {
    "LocationId": 124,
    "Latitude": 32.52129397,
    "Longitude": -92.07784092
  },
  {
    "LocationId": 125,
    "Latitude": 32.48050687,
    "Longitude": -92.1214555
  },
  {
    "LocationId": 126,
    "Latitude": 32.49038742,
    "Longitude": -92.10995486
  },
  {
    "LocationId": 127,
    "Latitude": 32.54073516,
    "Longitude": -92.1093775
  },
  {
    "LocationId": 128,
    "Latitude": 32.51002443,
    "Longitude": -92.12132286
  },
  {
    "LocationId": 129,
    "Latitude": 32.55686476,
    "Longitude": -92.11318406
  },
  {
    "LocationId": 130,
    "Latitude": 32.49890752,
    "Longitude": -92.12391973
  },
  {
    "LocationId": 131,
    "Latitude": 32.49297867,
    "Longitude": -92.12378327
  },
  {
    "LocationId": 132,
    "Latitude": 31.30555204,
    "Longitude": -92.45321997
  },
  {
    "LocationId": 133,
    "Latitude": 31.31105251,
    "Longitude": -92.4490212
  },
  {
    "LocationId": 134,
    "Latitude": 31.28918127,
    "Longitude": -92.45168939
  },
  {
    "LocationId": 135,
    "Latitude": 31.30620131,
    "Longitude": -92.4531987
  },
  {
    "LocationId": 136,
    "Latitude": 31.26560867,
    "Longitude": -92.46756065
  },
  {
    "LocationId": 137,
    "Latitude": 31.29947694,
    "Longitude": -92.4839453
  },
  {
    "LocationId": 138,
    "Latitude": 31.31045511,
    "Longitude": -92.44434983
  },
  {
    "LocationId": 139,
    "Latitude": 31.31061694,
    "Longitude": -92.45711237
  },
  {
    "LocationId": 140,
    "Latitude": 31.30897901,
    "Longitude": -92.44163413
  },
  {
    "LocationId": 141,
    "Latitude": 31.30667064,
    "Longitude": -92.438267
  },
  {
    "LocationId": 142,
    "Latitude": 31.30669497,
    "Longitude": -92.4562419
  },
  {
    "LocationId": 143,
    "Latitude": 30.06829867,
    "Longitude": -90.4844136
  },
  {
    "LocationId": 144,
    "Latitude": 30.08414987,
    "Longitude": -90.50202586
  },
  {
    "LocationId": 145,
    "Latitude": 30.069209,
    "Longitude": -90.49965353
  },
  {
    "LocationId": 146,
    "Latitude": 30.53550184,
    "Longitude": -92.0815125
  },
  {
    "LocationId": 147,
    "Latitude": 30.50352433,
    "Longitude": -92.07210103
  },
  {
    "LocationId": 148,
    "Latitude": 30.52991356,
    "Longitude": -92.0820259
  },
  {
    "LocationId": 149,
    "Latitude": 30.55656884,
    "Longitude": -92.0906928
  },
  {
    "LocationId": 150,
    "Latitude": 29.71475759,
    "Longitude": -91.19782033
  },
  {
    "LocationId": 151,
    "Latitude": 29.69535174,
    "Longitude": -91.20901406
  },
  {
    "LocationId": 152,
    "Latitude": 30.12729158,
    "Longitude": -91.84163785
  },
  {
    "LocationId": 153,
    "Latitude": 29.79367277,
    "Longitude": -91.50122673
  },
  {
    "LocationId": 154,
    "Latitude": 29.80468147,
    "Longitude": -91.51313066
  },
  {
    "LocationId": 155,
    "Latitude": 30.48287662,
    "Longitude": -90.10184573
  },
  {
    "LocationId": 156,
    "Latitude": 30.48296047,
    "Longitude": -90.09598356
  },
  {
    "LocationId": 157,
    "Latitude": 30.48185943,
    "Longitude": -90.09617018
  },
  {
    "LocationId": 158,
    "Latitude": 30.45757422,
    "Longitude": -90.13381973
  },
  {
    "LocationId": 159,
    "Latitude": 30.43200532,
    "Longitude": -90.0778298
  },
  {
    "LocationId": 160,
    "Latitude": 30.36386522,
    "Longitude": -90.0646747
  },
  {
    "LocationId": 161,
    "Latitude": 30.34564796,
    "Longitude": -90.01715057
  },
  {
    "LocationId": 162,
    "Latitude": 30.34728922,
    "Longitude": -90.0217626
  },
  {
    "LocationId": 163,
    "Latitude": 30.29785908,
    "Longitude": -89.71958632
  },
  {
    "LocationId": 164,
    "Latitude": 30.26526452,
    "Longitude": -89.78396232
  },
  {
    "LocationId": 165,
    "Latitude": 30.29109841,
    "Longitude": -89.73135239
  },
  {
    "LocationId": 166,
    "Latitude": 30.27021407,
    "Longitude": -89.7861764
  },
  {
    "LocationId": 167,
    "Latitude": 30.25021467,
    "Longitude": -89.78911826
  },
  {
    "LocationId": 168,
    "Latitude": 30.2729582,
    "Longitude": -89.78390874
  },
  {
    "LocationId": 169,
    "Latitude": 30.49988107,
    "Longitude": -90.4648707
  },
  {
    "LocationId": 170,
    "Latitude": 30.48853727,
    "Longitude": -90.48347673
  },
  {
    "LocationId": 171,
    "Latitude": 30.47635813,
    "Longitude": -90.46686749
  },
  {
    "LocationId": 172,
    "Latitude": 30.46417257,
    "Longitude": -90.54254256
  },
  {
    "LocationId": 173,
    "Latitude": 30.51255967,
    "Longitude": -90.53298286
  },
  {
    "LocationId": 174,
    "Latitude": 29.59797176,
    "Longitude": -90.70198046
  },
  {
    "LocationId": 175,
    "Latitude": 29.58045034,
    "Longitude": -90.72737883
  },
  {
    "LocationId": 176,
    "Latitude": 29.60083565,
    "Longitude": -90.71631217
  },
  {
    "LocationId": 177,
    "Latitude": 29.59515558,
    "Longitude": -90.7254876
  },
  {
    "LocationId": 178,
    "Latitude": 29.59641048,
    "Longitude": -90.70934079
  },
  {
    "LocationId": 179,
    "Latitude": 29.59186975,
    "Longitude": -90.72145685
  },
  {
    "LocationId": 180,
    "Latitude": 29.59246706,
    "Longitude": -90.703207
  },
  {
    "LocationId": 181,
    "Latitude": 29.58599296,
    "Longitude": -90.72365203
  },
  {
    "LocationId": 182,
    "Latitude": 29.97390998,
    "Longitude": -92.13179031
  },
  {
    "LocationId": 183,
    "Latitude": 31.14278767,
    "Longitude": -93.26099686
  },
  {
    "LocationId": 184,
    "Latitude": 31.13146537,
    "Longitude": -93.2658673
  },
  {
    "LocationId": 185,
    "Latitude": 31.07996495,
    "Longitude": -93.27310873
  },
  {
    "LocationId": 186,
    "Latitude": 30.77381802,
    "Longitude": -89.8716418
  },
  {
    "LocationId": 187,
    "Latitude": 32.61486807,
    "Longitude": -93.2914047
  },
  {
    "LocationId": 188,
    "Latitude": 32.61607231,
    "Longitude": -93.2806169
  },
  {
    "LocationId": 189,
    "Latitude": 31.92657946,
    "Longitude": -92.63747953
  },
  {
    "LocationId": 190,
    "Latitude": 30.24374877,
    "Longitude": -92.27553403
  },
  {
    "LocationId": 191,
    "Latitude": 30.24392527,
    "Longitude": -90.92193029
  },
  {
    "LocationId": 192,
    "Latitude": 30.23480937,
    "Longitude": -93.3921652
  },
  {
    "LocationId": 193,
    "Latitude": 29.95445997,
    "Longitude": -90.07872357
  },
  {
    "LocationId": 194,
    "Latitude": 30.49411568,
    "Longitude": -92.43574645
  },
  {
    "LocationId": 195,
    "Latitude": 30.37793433,
    "Longitude": -90.0926609
  },
  {
    "LocationId": 196,
    "Latitude": 30.20928145,
    "Longitude": -92.3717215
  },
  {
    "LocationId": 197,
    "Latitude": 32.50606467,
    "Longitude": -93.75404806
  },
  {
    "LocationId": 198,
    "Latitude": 32.53046787,
    "Longitude": -93.77937683
  },
  {
    "LocationId": 199,
    "Latitude": 32.49010217,
    "Longitude": -93.76504636
  },
  {
    "LocationId": 200,
    "Latitude": 32.50033538,
    "Longitude": -93.7283533
  },
  {
    "LocationId": 201,
    "Latitude": 30.19891213,
    "Longitude": -93.20954086
  },
  {
    "LocationId": 202,
    "Latitude": 30.44903372,
    "Longitude": -91.1724003
  },
  {
    "LocationId": 203,
    "Latitude": 30.49981369,
    "Longitude": -91.15759
  },
  {
    "LocationId": 204,
    "Latitude": 32.11174735,
    "Longitude": -91.6597364
  },
  {
    "LocationId": 205,
    "Latitude": 30.00520937,
    "Longitude": -91.8266145
  },
  {
    "LocationId": 206,
    "Latitude": 30.22956977,
    "Longitude": -92.02269783
  },
  {
    "LocationId": 207,
    "Latitude": 30.22796647,
    "Longitude": -92.02925673
  },
  {
    "LocationId": 208,
    "Latitude": 30.24428427,
    "Longitude": -91.9954166
  },
  {
    "LocationId": 209,
    "Latitude": 30.22958657,
    "Longitude": -92.02310746
  },
  {
    "LocationId": 210,
    "Latitude": 29.95998367,
    "Longitude": -90.06931496
  },
  {
    "LocationId": 211,
    "Latitude": 29.94335127,
    "Longitude": -90.07687273
  },
  {
    "LocationId": 212,
    "Latitude": 29.95772607,
    "Longitude": -90.09004783
  },
  {
    "LocationId": 213,
    "Latitude": 29.95445997,
    "Longitude": -90.07875576
  },
  {
    "LocationId": 214,
    "Latitude": 29.97098876,
    "Longitude": -90.09464447
  },
  {
    "LocationId": 215,
    "Latitude": 29.95639358,
    "Longitude": -90.0817582
  },
  {
    "LocationId": 216,
    "Latitude": 29.94417617,
    "Longitude": -90.0866867
  },
  {
    "LocationId": 217,
    "Latitude": 29.93055127,
    "Longitude": -90.07325186
  },
  {
    "LocationId": 218,
    "Latitude": 29.94075317,
    "Longitude": -90.08410955
  },
  {
    "LocationId": 219,
    "Latitude": 32.35875169,
    "Longitude": -92.1803543
  },
  {
    "LocationId": 220,
    "Latitude": 31.25501347,
    "Longitude": -92.439127
  },
  {
    "LocationId": 221,
    "Latitude": 31.30335561,
    "Longitude": -92.4726043
  },
  {
    "LocationId": 222,
    "Latitude": 29.95371237,
    "Longitude": -89.98268543
  },
  {
    "LocationId": 223,
    "Latitude": 30.53221303,
    "Longitude": -92.0914125
  },
  {
    "LocationId": 224,
    "Latitude": 30.54968681,
    "Longitude": -92.08323312
  },
  {
    "LocationId": 225,
    "Latitude": 30.54864323,
    "Longitude": -92.09194336
  },
  {
    "LocationId": 226,
    "Latitude": 30.27192941,
    "Longitude": -89.78297867
  },
  {
    "LocationId": 227,
    "Latitude": 30.30252737,
    "Longitude": -89.879332
  },
  {
    "LocationId": 228,
    "Latitude": 30.51221457,
    "Longitude": -90.53174066
  },
  {
    "LocationId": 229,
    "Latitude": 30.44883222,
    "Longitude": -90.45069963
  },
  {
    "LocationId": 230,
    "Latitude": 29.59139318,
    "Longitude": -90.724088
  },
  {
    "LocationId": 231,
    "Latitude": 29.5977816,
    "Longitude": -90.70503296
  }
]